oslotest/__init__.py
oslotest/base.py
oslotest/createfile.py
oslotest/log.py
oslotest/mock_fixture.py
oslotest/modules.py
oslotest/output.py
oslotest/timeout.py
oslotest/tests/__init__.py
oslotest/tests/unit/__init__.py
oslotest/tests/unit/test_base.py
oslotest/tests/unit/test_createfile.py
oslotest/tests/unit/test_log.py
oslotest/tests/unit/test_mock_fixture.py
oslotest/tests/unit/test_mockpatch.py
oslotest/tests/unit/test_modules.py
oslotest/tests/unit/test_output.py
oslotest/tests/unit/test_timeout.py
oslotest/tools/__init__.py
oslotest/tools/config.py
oslotest-6.0.0.data/scripts/oslo_debug_helper
oslotest-6.0.0.dist-info/AUTHORS
oslotest-6.0.0.dist-info/LICENSE
oslotest-6.0.0.dist-info/METADATA
oslotest-6.0.0.dist-info/WHEEL
oslotest-6.0.0.dist-info/pbr.json
oslotest-6.0.0.dist-info/top_level.txt
oslotest-6.0.0.dist-info/RECORD
